fake_uwsgi/__init__.py
fake_uwsgi/__pycache__/__init__.cpython-38.pyc
fake_uwsgi-1.1.0.dist-info/LICENSE.rst
fake_uwsgi-1.1.0.dist-info/METADATA
fake_uwsgi-1.1.0.dist-info/WHEEL
fake_uwsgi-1.1.0.dist-info/top_level.txt
fake_uwsgi-1.1.0.dist-info/RECORD
